sundata/__init__.py
sundata/sundata.py
sundata-1.0.0.dist-info/LICENCE
sundata-1.0.0.dist-info/METADATA
sundata-1.0.0.dist-info/WHEEL
sundata-1.0.0.dist-info/top_level.txt
sundata-1.0.0.dist-info/RECORD
