Metadata-Version: 2.1
Name: sundata
Version: 1.0.0
Summary: Simple module to get the angle of the Sun relative to the Horizon for a given geographic location and datetime.
Home-page: https://www.github.com/night-works/sundata
Author: Joseph McCarthy
Author-email: joseph@joemccarthy.co.uk
Project-URL: Bug Tracker, https://www.github.com/night-works/sundata/issues
Classifier: Programming Language :: Python :: 3
Classifier: License :: OSI Approved :: MIT License
Classifier: Operating System :: OS Independent
Requires-Python: >=3.6
License-File: LICENCE
Requires-Dist: docutils
Requires-Dist: pytest (==7.2.1)
Requires-Dist: pytest-cov (==4.0.0)
Requires-Dist: suntime (==1.2.5)
Requires-Dist: astropy[all] (==5.2.1)
Requires-Dist: pytz (==2022.7.1)
